<?xml version="1.0" encoding="UTF-8"?>
<feature
      id="org.eclipse.mylyn.experimental_sdk_feature"
      label="%featureName"
      version="3.1.0.qualifier"
      provider-name="%providerName"
      plugin="org.eclipse.mylyn">

   <description url="http://eclipse.org/mylyn">
      %description
   </description>

   <copyright>
      %copyright
   </copyright>

   <license url="license.html">
      %license
   </license>

   <url>
      <update label="%updateSiteName" url="http://download.eclipse.org/tools/mylyn/update/incubator"/>
   </url>

   <plugin
         id="org.eclipse.mylyn.sandbox.ui.source"
         download-size="0"
         install-size="0"
         version="0.0.0"
         unpack="false"/>

   <plugin
         id="org.eclipse.mylyn.monitor.usage.source"
         download-size="0"
         install-size="0"
         version="0.0.0"
         unpack="false"/>

   <plugin
         id="org.eclipse.mylyn.web.tasks.source"
         download-size="0"
         install-size="0"
         version="0.0.0"
         unpack="false"/>

   <plugin
         id="org.eclipse.mylyn.xplanner.core.source"
         download-size="0"
         install-size="0"
         version="0.0.0"
         unpack="false"/>

   <plugin
         id="org.eclipse.mylyn.xplanner.ui.source"
         download-size="0"
         install-size="0"
         version="0.0.0"
         unpack="false"/>

   <plugin
         id="org.eclipse.mylyn.wikitext.confluence.core.source"
         download-size="0"
         install-size="0"
         version="0.0.0"
         unpack="false"/>

   <plugin
         id="org.eclipse.mylyn.wikitext.confluence.ui.source"
         download-size="0"
         install-size="0"
         version="0.0.0"
         unpack="false"/>

   <plugin
         id="org.eclipse.mylyn.wikitext.core.source"
         download-size="0"
         install-size="0"
         version="0.0.0"
         unpack="false"/>

   <plugin
         id="org.eclipse.mylyn.wikitext.mediawiki.core.source"
         download-size="0"
         install-size="0"
         version="0.0.0"
         unpack="false"/>

   <plugin
         id="org.eclipse.mylyn.wikitext.mediawiki.ui.source"
         download-size="0"
         install-size="0"
         version="0.0.0"
         unpack="false"/>

   <plugin
         id="org.eclipse.mylyn.wikitext.textile.core.source"
         download-size="0"
         install-size="0"
         version="0.0.0"
         unpack="false"/>

   <plugin
         id="org.eclipse.mylyn.wikitext.textile.ui.source"
         download-size="0"
         install-size="0"
         version="0.0.0"
         unpack="false"/>

   <plugin
         id="org.eclipse.mylyn.wikitext.tracwiki.core.source"
         download-size="0"
         install-size="0"
         version="0.0.0"
         unpack="false"/>

   <plugin
         id="org.eclipse.mylyn.wikitext.tracwiki.ui.source"
         download-size="0"
         install-size="0"
         version="0.0.0"
         unpack="false"/>

   <plugin
         id="org.eclipse.mylyn.wikitext.ui.source"
         download-size="0"
         install-size="0"
         version="0.0.0"
         unpack="false"/>

</feature>
